aioetcd3/__init__.py
aioetcd3/auth.py
aioetcd3/base.py
aioetcd3/client.py
aioetcd3/cluster.py
aioetcd3/exceptions.py
aioetcd3/help.py
aioetcd3/kv.py
aioetcd3/lease.py
aioetcd3/maintenance.py
aioetcd3/transaction.py
aioetcd3/utils.py
aioetcd3/watch.py
aioetcd3/_etcdv3/__init__.py
aioetcd3/_etcdv3/auth_pb2.py
aioetcd3/_etcdv3/auth_pb2_grpc.py
aioetcd3/_etcdv3/kv_pb2.py
aioetcd3/_etcdv3/kv_pb2_grpc.py
aioetcd3/_etcdv3/rpc_pb2.py
aioetcd3/_etcdv3/rpc_pb2_grpc.py
test/__init__.py
test/test_auth.py
test/test_cluster.py
test/test_kv.py
test/test_lease.py
test/test_watch.py
test/utils.py
aioetcd3-1.13.dist-info/METADATA
aioetcd3-1.13.dist-info/WHEEL
aioetcd3-1.13.dist-info/top_level.txt
aioetcd3-1.13.dist-info/RECORD
