Metadata-Version: 2.1
Name: aioetcd3
Version: 1.13
Summary: asyncio wrapper for etcd v3
Home-page: https://github.com/gaopeiliang/aioetcd3
Author: gaopeiliang
Author-email: 964911957@qq.com
License: Apache
Platform: any
Classifier: License :: OSI Approved :: MIT License
Classifier: Intended Audience :: Developers
Classifier: Framework :: AsyncIO
Classifier: Programming Language :: Python
Classifier: Programming Language :: Python :: 3
Classifier: Programming Language :: Python :: 3.6
Classifier: Topic :: Software Development
Classifier: Framework :: AsyncIO
Requires-Python: >=3.6
Requires-Dist: aiogrpc (>=1.4)
Requires-Dist: protobuf
